oi_platform_client/__init__.py
oi_platform_client/cfg.py
oi_platform_client/converter.py
oi_platform_client/dataset.py
oi_platform_client/lib.py
oi_platform_client/main.py
oi_platform_client/retrieve.py
oi_platform_client/schema.py
oi_platform_client/units.py
oi_platform_client-0.0.1.dist-info/METADATA
oi_platform_client-0.0.1.dist-info/WHEEL
oi_platform_client-0.0.1.dist-info/top_level.txt
oi_platform_client-0.0.1.dist-info/RECORD
